pygeez/__init__.py
pygeez/__main__.py
pygeez/assistant.py
pygeez/config.py
pygeez/decorator.py
pygeez/exceptions.py
pygeez/xd.py
pygeez/Clients/__init__.py
pygeez/Clients/client.py
pygeez/Clients/startup.py
pygeez/dB/__init__.py
pygeez/dB/_core.py
pygeez/dB/afk_db.py
pygeez/dB/antiflood_db.py
pygeez/dB/asst_fns.py
pygeez/dB/asstcmd_db.py
pygeez/dB/autoban_db.py
pygeez/dB/blacklist_chat_db.py
pygeez/dB/blacklist_db.py
pygeez/dB/botchat_db.py
pygeez/dB/broadcast_db.py
pygeez/dB/ch_db.py
pygeez/dB/dnd_db.py
pygeez/dB/echo_db.py
pygeez/dB/filestore_db.py
pygeez/dB/filter_db.py
pygeez/dB/forcesub_db.py
pygeez/dB/gban_mute_db.py
pygeez/dB/gcast_blacklist_db.py
pygeez/dB/greetings_db.py
pygeez/dB/logusers_db.py
pygeez/dB/mute_db.py
pygeez/dB/night_db.py
pygeez/dB/notes_db.py
pygeez/dB/nsfw_db.py
pygeez/dB/pmpermit_db.py
pygeez/dB/snips_db.py
pygeez/dB/vc_sudos.py
pygeez/dB/warn_db.py
pygeez/methods/Inline.py
pygeez/methods/__init__.py
pygeez/methods/_database.py
pygeez/methods/_misc.py
pygeez/methods/converter.py
pygeez/methods/func.py
pygeez/methods/helpers.py
pygeez/methods/hosting.py
pygeez/methods/queue.py
pygeez/pyrogram/__init__.py
pygeez/pyrogram/_wrappers.py
pygeez/pyrogram/func.py
pygeez/pyrogram/misc.py
pygeez/pyrogram/pastebin.py
pygeez/pyrogram/sections.py
pygeez/pyrogram/toolbot.py
pygeez/pyrogram/tools.py
pygeez/resources/__init__.py
pygeez/telethon/__init__.py
pygeez/telethon/dB/__init__.py
pygeez/telethon/dB/_core.py
pygeez/telethon/dB/afk_db.py
pygeez/telethon/dB/antiflood_db.py
pygeez/telethon/dB/asst_fns.py
pygeez/telethon/dB/asstcmd_db.py
pygeez/telethon/dB/autoban_db.py
pygeez/telethon/dB/blacklist_chat_db.py
pygeez/telethon/dB/blacklist_db.py
pygeez/telethon/dB/botchat_db.py
pygeez/telethon/dB/broadcast_db.py
pygeez/telethon/dB/ch_db.py
pygeez/telethon/dB/dnd_db.py
pygeez/telethon/dB/echo_db.py
pygeez/telethon/dB/filestore_db.py
pygeez/telethon/dB/filter_db.py
pygeez/telethon/dB/forcesub_db.py
pygeez/telethon/dB/gban_mute_db.py
py_geez-2.0.1.dist-info/LICENSE
py_geez-2.0.1.dist-info/METADATA
py_geez-2.0.1.dist-info/NOTICE
py_geez-2.0.1.dist-info/WHEEL
py_geez-2.0.1.dist-info/top_level.txt
py_geez-2.0.1.dist-info/RECORD
